Workbook
Name NativeTimeline_Check_In_Date: #N/A
Name Slicer_Booking_Source: #N/A
Name Slicer_Guest_Country: #N/A
Name Slicer_Payment_Status: #N/A
Name Slicer_Room_Type: #N/A

Sheet Data_Dictionary
A1: Motel Booking Data Dictionary
A3: Column | B3: Meaning | C3: Expected Type | D3: Example
A4: Booking_ID | B4: Unique booking reference | C4: Text | D4: BK1001
A5: Booking_Date | B5: Date the reservation was created | C5: Date | D5: 15-Jan-2025
A6: Check_In_Date | B6: Guest arrival date | C6: Date | D6: 10-Feb-2025
A7: Check_Out_Date | B7: Guest departure date | C7: Date | D7: 13-Feb-2025
A8: Room_Number | B8: Assigned motel room | C8: Whole number | D8: 108
A9: Room_Type | B9: Type of room booked | C9: Category | D9: Standard
A10: Booking_Source | B10: Where the booking came from | C10: Category | D10: Expedia
A11: Guest_Country | B11: Guest's country | C11: Category | D11: United Kingdom
A12: Adults | B12: Number of adult guests | C12: Whole number | D12: 2
A13: Nightly_Rate_GBP | B13: Room price per night | C13: Currency | D13: £95.00
A14: Resort_Fee_GBP | B14: Extra fee per booking | C14: Currency | D14: £8.50
... A17: Guest_Rating | B17: Guest score from 1 to 5 | C17: Decimal/Whole number | D17: 4

Sheet Raw_Motel_Data
A1: Booking_ID | B1: Booking_Date | C1: Check_In_Date | D1: Check_Out_Date | E1: Room_Number | F1: Room_Type | G1: Booking_Source | H1: Guest_Country | I1: Adults | J1: Nightly_Rate_GBP | K1: Resort_Fee_GBP | L1: Booking_Status | M1: Payment_Status | N1: Guest_Rating
A2: BK1001 | B2: 45988 | C2: 45990 | D2: 45991 | E2: 118 | F2: Deluxe | G2: Expedia | H2: United States | I2: 4 | J2: 98.07 | K2: 8.5 | L2: Completed | M2: Paid | N2: 5
A3: BK1002 | B3: 45877 | C3: 45879 | D3: 45880 | E3: 106 | F3: Deluxe | G3: Expedia | H3: Germany | I3: 3 | J3: 95.8 | K3: 8.5 | L3: Completed | M3: Paid | N3: 5
A4: BK1003 | B4: 45848 | C4: 45877 | D4: 45879 | E4: 218 | F4: King | G4: Direct | H4: Australia | I4: 2 | J4: 134.43 | K4: 8.5 | L4: Completed | M4: Paid | N4: 4
A5: BK1004 | B5: 45690 | C5: 45715 | D5: 45716 | E5: 107 | F5: King | G5: Booking.com | H5: Germany | I5: 2 | J5: 138.25 | K5: 8.5 | L5: Completed | M5: Paid | N5: 4
A6: BK1005 | B6: 45684 | C6: 45703 | D6: 45708 | E6: 220 | F6: King | G6: Expedia | H6: France | I6: 1 | J6: 111.6 | K6: 8.5 | L6: Completed | M6: Paid | N6: 3
A7: BK1006 | B7: 45757 | C7: 45782 | D7: 45783 | E7: 118 | F7: standard | G7: Booking.com | H7: United States | I7: 2 | J7: 95.66 | K7: 8.5 | L7: Completed | M7: Paid | N7: 5
A8: BK1007 | B8: 45955 | C8: 45994 | D8: 45995 | E8: 111 | F8: Deluxe | G8: Expedia | H8: Canada | I8: 2 | J8: 103.1 | K8: 8.5 | L8: Cancelled | M8: Refunded
A9: BK1008 | B9: 45959 | C9: 46013 | D9: 46016 | E9: 104 | G9: Direct | H9: Australia | I9: 2 | J9: 107.03 | K9: 8.5 | L9: Completed | M9: Paid | N9: 5
A10: BK1009 | B10: 45782 | C10: 45824 | D10: 45826 | E10: 212 | F10: Double | G10: Walk-in | H10: United States | I10: 2 | J10: 89.19 | K10: 8.5 | L10: Completed | M10: Paid | N10: 5
A11: BK1010 | B11: 45904 | C11: 45962 | D11: 45966 | E11: 218 | F11: Double | G11: expedia | H11: United States | I11: 2 | J11: 100.29 | K11: 8.5 | L11: Completed | M11: Paid | N11: 3
A12: BK1011 | B12: 45690 | C12: 45741 | D12: 45743 | E12: 208 | F12: Standard | G12: Walk-in | H12: Canada | I12: 3 | J12: 94.9 | K12: 8.5 | L12: Completed | M12: Pending | N12: 3
A13: BK1012 | B13: 45967 | C13: 46011 | D13: 46012 | E13: 215 | F13: King | G13: Booking.com | H13: United Kingdom | I13: 2 | J13: 125.22 | K13: 8.5 | L13: completed | M13: Pending | N13: 5
A14: BK1013 | B14: 45748 | C14: 45797 | D14: 45802 | E14: 112 | F14: Standard | H14: Australia | I14: 4 | J14: 82.69 | K14: 8.5 | L14: Completed | M14: Paid | N14: 4
A15: BK1014 | B15: 45880 | C15: 45939 | D15: 45944 | E15: 101 | F15: King | G15: Walk-in | H15: United Kingdom | I15: 1 | J15: 142.52 | K15: 8.5 | L15: Cancelled | M15: Pending
A16: BK1015 | B16: 45769 | C16: 45785 | D16: 45786 | E16: 217 | F16: Standard | G16: Direct | H16: France | I16: 2 | J16: 90.4 | K16: 8.5 | L16: No-Show | M16: Pending
A17: BK1016 | B17: 45692 | C17: 45728 | D17: 45732 | E17: 111 | F17: King | G17: Walk-in | H17: United States | I17: 3 | J17: 136.43 | K17: 8.5 | L17: Completed | M17: Paid | N17: 4
A18: BK1017 | B18: 45977 | C18: 46006 | D18: 46009 | E18: 214 | F18: DELUXE | G18: Direct | H18: United States | I18: 2 | J18: 86.92 | K18: 8.5 | L18: Completed | M18: Paid | N18: 5
A19: BK1018 | B19: 45770 | C19: 45775 | D19: 45776 | E19: 104 | F19: Deluxe | G19: Direct | H19: United Kingdom | I19: 2 | J19: 97.13 | K19: 8.5 | L19: Completed | M19: Paid | N19: 4
A20: BK1019 | B20: 45892 | C20: 45939 | D20: 45941 | E20: 217 | F20: Double | G20: Expedia | I20: 2 | J20: 109.22 | K20: 8.5 | L20: Completed | M20: Paid | N20: 4
A21: BK1020 | B21: 45817 | C21: 45844 | D21: 45848 | E21: 210 | F21: Standard | G21: Direct | H21: United Kingdom | I21: 2 | J21: 88.21 | K21: 8.5 | L21: Cancelled | M21: Refunded
A22: BK1021 | B22: 45777 | C22: 45790 | D22: 45792 | E22: 215 | F22: Double | G22: Expedia | H22: Canada | I22: 2 | J22: 93.36 | K22: 8.5 | L22: Completed | M22: paid | N22: 4
A23: BK1022 | B23: 45940 | C23: 45944 | D23: 45945 | E23: 215 | F23: Standard | G23: Direct | H23: Australia | I23: 2 | J23: 74.16 | K23: 8.5 | L23: Completed | M23: Paid | N23: 4
A24: BK1023 | B24: 45668 | C24: 45693 | D24: 45695 | E24: 101 | F24: Double | G24: Booking.com | H24: Australia | I24: 2 | K24: 8.5 | L24: Completed | M24: Paid | N24: 5
A25: BK1024 | B25: 45991 | C25: 46001 | D25: 46005 | E25: 113 | F25: King | G25: Expedia | H25: United Kingdom | I25: 3 | J25: 135.75 | K25: 8.5 | L25: Completed | M25: Paid | N25: 3
A26: BK1025 | B26: 45929 | C26: 45962 | D26: 45966 | E26: 214 | F26: Deluxe | G26: Direct | H26: Germany | I26: 1 | J26: 120.54 | K26: 8.5 | L26: Completed | M26: Paid | N26: 4
A27: BK1026 | B27: 04/06/2025 | C27: 45869 | D27: 45870 | E27: 217 | F27: Deluxe | G27: Direct | H27: Germany | I27: 1 | J27: 107.58 | K27: 8.5 | L27: Completed | M27: Paid | N27: 4
A28: BK1027 | B28: 45751 | C28: 45767 | D28: 45770 | E28: 117 | F28: Double | G28: Expedia | H28: France | I28: 4 | J28: 94 | K28: 8.5 | L28: Completed | M28: Paid | N28: 3
A29: BK1028 | B29: 45627 | C29: 45667 | D29: 45671 | E29: 217 | F29: Standard | G29: Direct | H29: Germany | I29: 2 | J29: 82.65 | K29: 8.5 | L29: Completed | M29: Paid | N29: 3
A30: BK1029 | B30: 45769 | C30: 45788 | D30: 45791 | E30: 111 | G30: Booking.com | H30: Germany | I30: 4 | J30: 100.87 | K30: 8.5 | L30: Completed | M30: Paid | N30: 5
A31: BK1030 | B31: 45699 | C31: 45716 | D31: 45718 | E31: 108 | F31: Standard | G31: Expedia | H31: India | I31: 2 | J31: 85.12 | K31: 8.5 | L31: Completed | M31: Paid | N31: 5
A32: BK1031 | B32: 45766 | C32: 45798 | D32: 45803 | E32: 117 | F32: Standard | G32: Direct | H32: France | I32: 2 | J32: 90.73 | K32: 8.5 | L32: Completed | M32: Paid | N32: 4
A33: BK1032 | B33: 45978 | C33: 45989 | D33: 45992 | E33: 209 | F33: Double | G33: BOOKING.COM | H33: United Kingdom | I33: 1 | J33: 113.35 | K33: 8.5 | L33: Completed | M33: Paid | N33: 3
A34: BK1033 | B34: 45816 | C34: 45852 | D34: 45857 | E34: 110 | F34: Double | G34: Expedia | H34: United Kingdom | I34: 2 | J34: 95.94 | K34: 8.5 | L34: Cancelled | M34: Refunded
A35: BK1034 | B35: 45802 | C35: 45846 | D35: 45848 | E35: 116 | F35: Standard | G35: Booking.com | H35: Australia | I35: 3 | J35: 92.1 | K35: 8.5 | L35: Completed | M35: Paid | N35: 4
A36: BK1035 | B36: 45732 | C36: 45784 | D36: 45786 | E36: 112 | F36: Double | G36: Direct | H36: United States | I36: 4 | J36: 112.73 | K36: 8.5 | L36: Cancelled | M36: Pending
A37: BK1036 | B37: 45987 | C37: 46005 | D37: 46007 | E37: 111 | F37: Standard | G37: Walk-in | H37: Australia | I37: 1 | J37: 91.46 | L37: Completed | M37: Paid | N37: 4
A38: BK1037 | B38: 45789 | C38: 45842 | D38: 45845 | E38: 115 | F38: Deluxe | G38: Direct | H38: France | I38: 2 | J38: 106.95 | K38: 8.5 | L38: Completed | M38: Paid | N38: 4
A39: BK1038 | B39: 45816 | C39: 45842 | D39: 45847 | E39: 215 | F39: King | G39: Direct | H39: United Kingdom | I39: 2 | J39: 116.25 | K39: 8.5 | L39: No-Show | M39: Paid
A40: BK1039 | B40: 45643 | C40: 45682 | D40: 45683 | E40: 208 | F40: King | G40: Booking.com | H40: Canada | I40: 3 | J40: 144.45 | K40: 8.5 | L40: Completed | M40: Paid | N40: 4
A41: BK1040 | B41: 45747 | C41: 45793 | D41: 45794 | E41: 208 | F41: Standard | G41: Expedia | H41: India | I41: 2 | J41: 71.75 | K41: 8.5 | L41: Completed | M41: Paid | N41: 4
A42: BK1041 | B42: 45955 | C42: 46002 | D42: 46003 | E42: 120 | F42: King | G42: Walk-in | H42: India | I42: 2 | J42: 134.4 | K42: 8.5 | L42: Completed | M42: Paid | N42: 5
A43: BK1042 | B43: 45817 | C43: 45857 | D43: 45859 | E43: 217 | F43: King | G43: Walk-in | H43: Germany | I43: 1 | J43: 120.64 | K43: 8.5 | L43: Completed | M43: Paid | N43: 5
A44: BK1043 | B44: 45968 | C44: 45998 | D44: 46001 | E44: 209 | F44: Double | G44: Expedia | H44: Germany | I44: 2 | J44: 108.81 | K44: 8.5 | L44: No-Show | M44: Pending
A45: BK1044 | B45: 45981 | C45: 46000 | D45: 46001 | E45: 213 | F45: King | G45: Direct | H45: Australia | I45: 2 | J45: 133.55 | K45: 8.5 | L45: cancelled | M45: Paid | N45: 3
A46: BK1045 | B46: 45655 | C46: 45686 | D46: 45688 | E46: 220 | F46: Standard | G46: Walk-in | H46: Canada | I46: 4 | J46: 84.39 | K46: 8.5 | L46: Completed | M46: Paid | N46: 4
A47: BK1046 | B47: 45745 | C47: 45787 | D47: 45789 | E47: 101 | F47: Standard | H47: United States | I47: 2 | J47: 90.1 | K47: 8.5 | L47: Completed | M47: Paid | N47: 5
A48: BK1047 | B48: 45760 | C48: 05-13-2025 | D48: 45791 | E48: 109 | F48: Double | G48: Booking.com | H48: Australia | I48: 2 | J48: 103.38 | K48: 8.5 | L48: Completed | M48: Paid | N48: 5
A49: BK1048 | B49: 45843 | C49: 45891 | D49: 45893 | E49: 211 | F49: Double | G49: Booking.com | H49: Australia | I49: 2 | J49: 110.2 | K49: 8.5 | L49: Completed | M49: Paid | N49: 4
A50: BK1049 | B50: 45965 | C50: 45983 | D50: 45985 | E50: 209 | F50: Standard | G50: Booking.com | H50: United States | I50: 2 | J50: 78.4 | K50: 8.5 | L50: Cancelled | M50: Refunded
A51: BK1050 | B51: 45718 | C51: 45733 | D51: 45735 | E51: 205 | F51: Deluxe | G51: Expedia | H51: United Kingdom | I51: 2 | J51: 107.23 | K51: 8.5 | L51: Completed | M51: Paid | N51: 4
A52: BK1051 | B52: 45820 | C52: 45878 | D52: 45882 | E52: 218 | F52: Standard | G52: Walk-in | H52: Canada | I52: 1 | J52: 93.57 | K52: 8.5 | L52: Completed | M52: Paid | N52: 4
A53: BK1052 | B53: 45886 | C53: 45938 | D53: 45943 | E53: 219 | F53: Deluxe | G53: Walk-in | H53: United States | I53: 2 | J53: 108.08 | K53: 8.5 | L53: Completed | M53: Paid
A54: BK1053 | B54: 45816 | C54: 45870 | D54: 45872 | E54: 210 | F54: Deluxe | G54: Walk-in | H54: Canada | I54: 3 | J54: 111.93 | K54: 8.5 | L54: Completed | M54: Paid | N54: 4
A55: BK1054 | B55: 45895 | C55: 45899 | D55: 45901 | E55: 117 | F55: Double | G55: Booking.com | H55: United States | I55: 2 | J55: 94.81 | K55: 8.5 | L55: Completed | M55: Paid | N55: 4
A56: BK1055 | B56: 45761 | C56: 45792 | D56: 45793 | E56: 102 | F56: Standard | G56: Booking.com | H56: United States | I56: 4 | J56: 71.72 | K56: 8.5 | L56: No-Show | M56: Pending
A57: BK1056 | B57: 45665 | C57: 45678 | D57: 45680 | E57: 102 | F57: Deluxe | G57: Expedia | H57: United States | I57: 2 | J57: 115.08 | K57: 8.5 | L57: Completed | M57: Paid | N57: 5
A58: BK1057 | B58: 45783 | C58: 45794 | D58: 45797 | E58: 219 | F58: Standard | G58: Expedia | I58: 1 | J58: 84.47 | K58: 8.5 | L58: Cancelled | M58: Pending
A59: BK1058 | B59: 45861 | C59: 45866 | D59: 45868 | E59: 218 | F59: Deluxe | G59: Direct | H59: France | I59: 2 | J59: 120.51 | K59: 8.5 | L59: Completed | M59: Paid | N59: 5
A60: BK1059 | B60: 45649 | C60: 45684 | D60: 45687 | E60: 208 | F60: King | G60: Direct | H60: Germany | I60: 4 | J60: 0 | K60: 8.5 | L60: Cancelled | M60: Pending
A61: BK1060 | B61: 45693 | C61: 45717 | D61: 45721 | E61: 210 | F61: Deluxe | G61: Walk-in | H61: United States | I61: 4 | J61: 110.65 | K61: 8.5 | L61: Completed | M61: Paid | N61: 5
A62: BK1061 | B62: 45882 | C62: 45910 | D62: 45914 | E62: 218 | F62: King | G62: Booking.com | H62: Australia | I62: 2 | J62: 139.08 | K62: 8.5 | L62: Completed | M62: Paid | N62: 4
A63: BK1062 | B63: 45860 | C63: 45900 | D63: 45905 | E63: 205 | F63: King | G63: Direct | H63: Canada | I63: 2 | J63: 116.36 | K63: 8.5 | L63: Completed | M63: PENDING | N63: 4
A64: BK1063 | B64: 45761 | C64: 45806 | D64: 45811 | E64: 118 | F64: Standard | G64: Expedia | H64: United Kingdom | I64: 2 | J64: 88 | K64: 8.5 | L64: Completed | M64: Paid | N64: 5
A65: BK1064 | B65: 45877 | C65: 45906 | D65: 45910 | E65: 102 | F65: Standard | G65: Booking.com | H65: United States | I65: 2 | J65: 87.29 | K65: 8.5 | L65: Completed | M65: Paid | N65: 4
A66: BK1065 | B66: 45923 | C66: 45946 | D66: 45951 | E66: 208 | F66: King | G66: Booking.com | H66: France | I66: 2 | J66: 119.48 | K66: 8.5 | L66: Completed | M66: Paid | N66: 4
A67: BK1066 | B67: 45776 | C67: 45824 | E67: 215 | F67: Deluxe | G67: Expedia | H67: United States | I67: 4 | J67: 109.53 | K67: 8.5 | L67: Completed | M67: Pending | N67: 5
A68: BK1067 | B68: 45961 | C68: 45968 | D68: 45971 | E68: 113 | F68: King | G68: Expedia | H68: India | I68: 2 | J68: 120.58 | K68: 8.5 | L68: Completed | M68: Paid | N68: 3
A69: BK1068 | B69: 45671 | C69: 45690 | D69: 45695 | E69: 109 | G69: Direct | H69: Australia | I69: 1 | J69: 102.22 | K69: 8.5 | L69: Completed | M69: Paid | N69: 4
A70: BK1069 | B70: 45633 | C70: 45689 | D70: 45692 | E70: 211 | F70: Standard | G70: Direct | H70: Canada | I70: 2 | J70: 71.85 | K70: 8.5 | L70: Completed | M70: Paid | N70: 4
A71: BK1070 | B71: 45945 | C71: 45951 | D71: 45954 | E71: 116 | F71: Standard | G71: Walk-in | H71: Germany | I71: 3 | J71: 89.77 | K71: 8.5 | L71: Completed | M71: Paid | N71: 4
A72: BK1071 | B72: 45833 | C72: 45889 | D72: 45892 | E72: 218 | F72: Double | G72: Booking.com | H72: Germany | I72: 3 | J72: 86.81 | K72: 8.5 | L72: No-Show | M72: Pending
A73: BK1072 | B73: 45752 | C73: 45769 | D73: 45771 | E73: 106 | F73: Deluxe | G73: Expedia | H73: United States | I73: 3 | J73: 97.25 | K73: 8.5 | L73: Completed | M73: Paid | N73: 5
A74: BK1073 | B74: 45900 | C74: 45903 | D74: 45906 | E74: 115 | F74: King | G74: direct | H74: France | I74: 2 | J74: 112.49 | K74: 8.5 | L74: Completed | M74: Paid | N74: 5
A75: BK1074 | B75: 45936 | C75: 45964 | D75: 45966 | E75: 108 | F75: Deluxe | G75: Expedia | H75: India | I75: 2 | J75: 97.14 | K75: 8.5 | L75: Completed | M75: Paid | N75: 5
A76: BK1075 | B76: 45925 | C76: 45954 | D76: 45957 | E76: 108 | F76: Double | G76: Booking.com | H76: France | I76: 2 | K76: 8.5 | L76: Completed | M76: Paid | N76: 3
A77: BK1076 | B77: 45912 | C77: 45969 | D77: 45970 | E77: 208 | F77: King | G77: Booking.com | H77: United Kingdom | I77: 1 | J77: 118.01 | K77: 8.5 | L77: Completed | M77: Paid | N77: 5
A78: BK1077 | B78: 45636 | C78: 45673 | D78: 45676 | E78: 103 | F78: Deluxe | G78: Walk-in | H78: Germany | I78: 4 | J78: 108.27 | K78: 8.5 | L78: Completed | M78: Pending | N78: 4
A79: BK1078 | B79: 45982 | C79: 45988 | D79: 45992 | E79: 211 | F79: King | G79: Walk-in | H79: India | I79: 2 | J79: 133.45 | K79: 8.5 | L79: Cancelled | M79: Pending
A80: BK1079 | B80: 45854 | C80: 45873 | D80: 45877 | E80: 206 | F80: Standard | G80: Walk-in | H80: United Kingdom | I80: 2 | J80: 76.31 | K80: 8.5 | L80: Completed | M80: Paid | N80: 5
A81: BK1080 | B81: 45633 | C81: 45663 | D81: 45668 | E81: 207 | F81: Standard | G81: Expedia | H81: Germany | I81: 2 | J81: 85.57 | K81: 8.5 | L81: Completed | M81: Paid | N81: 3
A82: BK1081 | B82: 45731 | C82: 45767 | D82: 45770 | E82: 109 | F82: King | G82: Walk-in | H82: France | I82: 2 | J82: 114.25 | K82: 8.5 | L82: No-Show | M82: Pending
A83: BK1082 | B83: 45708 | C83: 45744 | D83: 45747 | E83: 101 | F83: Double | H83: United States | I83: 1 | J83: 98.84 | K83: 8.5 | L83: Completed | M83: Paid | N83: 4
A84: BK1083 | B84: 45766 | C84: 45812 | D84: 45817 | E84: 118 | F84: Double | G84: Walk-in | H84: Canada | I84: 2 | J84: 98.7 | K84: 8.5 | L84: Completed | M84: Paid | N84: 5
A85: BK1084 | B85: 45867 | C85: 45923 | D85: 45922 | E85: 105 | F85: King | G85: Walk-in | H85: India | I85: 3 | J85: 119.35 | K85: 8.5 | L85: Completed | M85: Paid | N85: 5
A86: BK1085 | B86: 45903 | C86: 45959 | D86: 45963 | E86: 110 | F86: Double | G86: Walk-in | H86: India | I86: 2 | J86: 101.56 | K86: 8.5 | L86: Completed | M86: Paid | N86: 4
A87: BK1086 | B87: 45722 | C87: 45759 | D87: 45761 | E87: 205 | F87: Deluxe | G87: Walk-in | H87: United Kingdom | I87: 2 | J87: 117.34 | K87: 8.5 | L87: Completed | M87: Paid | N87: 4
A88: BK1087 | B88: 45970 | C88: 46002 | D88: 46004 | E88: 103 | F88: Deluxe | G88: Booking.com | H88: Australia | I88: 1 | J88: 121.23 | K88: 8.5 | L88: Completed | M88: Paid | N88: 4
A89: BK1088 | B89: 45643 | C89: 45670 | D89: 45672 | E89: 110 | F89: Standard | G89: Walk-in | H89: Australia | I89: 2 | J89: 78.46 | K89: 8.5 | L89: Completed | M89: Paid | N89: 4
A90: BK1089 | B90: 45983 | C90: 46008 | D90: 46013 | E90: 201 | F90: Double | G90: Direct | H90: Germany | I90: 1 | J90: 92.04 | K90: 8.5 | L90: Completed | M90: Paid | N90: 4
A91: BK1090 | B91: 45702 | C91: 45709 | D91: 45713 | E91: 107 | F91: Double | G91: Expedia | H91: France | I91: 2 | J91: 112.1 | K91: 8.5 | L91: No show | M91: Paid | N91: 4
A92: BK1091 | B92: 45818 | C92: 45846 | D92: 45849 | E92: 110 | F92: Deluxe | G92: Walk-in | H92: Germany | I92: 4 | J92: 118.78 | L92: Completed | M92: Paid | N92: 4
A93: BK1092 | B93: 45948 | C93: 45980 | D93: 45982 | E93: 218 | F93: Deluxe | G93: Expedia | H93: Canada | I93: 4 | J93: 102.62 | K93: 8.5 | L93: Completed | M93: Paid | N93: 4
A94: BK1093 | B94: 45799 | C94: 45810 | D94: 45815 | E94: 105 | F94: Double | G94: Booking.com | H94: Germany | I94: 2 | J94: 104.17 | K94: 8.5 | L94: Completed | M94: Paid | N94: 4
A95: BK1094 | B95: 45709 | C95: 45764 | D95: 45768 | E95: 211 | F95: Standard | G95: Expedia | H95: Canada | I95: 3 | J95: 78.97 | K95: 8.5 | L95: Completed | M95: Paid
A96: BK1095 | B96: 45982 | C96: 46000 | D96: 46004 | E96: 101 | F96: Standard | G96: Walk-in | H96: Australia | I96: 2 | J96: 89.39 | K96: 8.5 | L96: Completed | M96: Paid | N96: 4
A97: BK1096 | B97: 45948 | C97: 45988 | D97: 45990 | E97: 117 | F97: Deluxe | G97: Direct | H97: France | I97: 4 | J97: 96.18 | K97: 8.5 | L97: Cancelled | M97: Refunded
A98: BK1097 | B98: 45912 | C98: 45959 | D98: 45962 | E98: 109 | F98: Standard | G98: Booking.com | H98: India | I98: 4 | J98: 450 | K98: 8.5 | L98: Completed | M98: Paid | N98: 4
A99: BK1098 | B99: 45875 | C99: 45934 | D99: 45939 | E99: 118 | F99: Deluxe | G99: Booking.com | H99: Australia | I99: 2 | J99: 124.02 | K99: 8.5 | L99: Completed | M99: Paid | N99: 3
A100: BK1099 | B100: 45892 | C100: 45902 | D100: 45903 | E100: 115 | F100: Double | G100: Booking.com | H100: United Kingdom | I100: 2 | J100: 85.42 | K100: 8.5 | L100: Completed | M100: Refunded | N100: 5
...

Sheet Cleaned_Motel_Booking_Data
A1: Booking_ID | B1: Check_In_Date | C1: Room_Number | D1: Room_Type | E1: Booking_Source | F1: Guest_Country | G1: Adults | H1: Nightly_Rate_GBP | I1: Resort_Fee_GBP | J1: Booking_Status | K1: Payment_Status | L1: Guest_Rating | M1: Booking_Date | N1: Check_Out_Date | O1: Nights | P1: Estimated_Revenue_GBP
A2: BK1098 | B2: 45934 | C2: 118 | D2: Deluxe | E2: Booking.com | F2: Australia | G2: 2 | H2: 124.02 | I2: 8.5 | J2: Completed | K2: Paid | L2: 3 | M2: 45875 | N2: 45939 | O2: 5 | P2: 628.6
A3: BK1065 | B3: 45946 | C3: 208 | D3: King | E3: Booking.com | F3: France | G3: 2 | H3: 119.48 | I3: 8.5 | J3: Completed | K3: Paid | L3: 4 | M3: 45923 | N3: 45951 | O3: 5 | P3: 605.9
A4: BK1062 | B4: 45900 | C4: 205 | D4: King | E4: Direct | F4: Canada | G4: 2 | H4: 116.36 | I4: 8.5 | J4: Completed | K4: Pending | L4: 4 | M4: 45860 | N4: 45905 | O4: 5 | P4: 590.3
A5: BK1120 | B5: 45911 | C5: 207 | D5: King | E5: Expedia | F5: Australia | G5: 3 | H5: 113.98 | I5: 8.5 | J5: Completed | K5: Paid | L5: 5 | M5: 45882 | N5: 45916 | O5: 5 | P5: 578.4
A6: BK1005 | B6: 45703 | C6: 220 | D6: King | E6: Expedia | F6: France | G6: 1 | H6: 111.6 | I6: 8.5 | J6: Completed | K6: Paid | L6: 3 | M6: 45684 | N6: 45708 | O6: 5 | P6: 566.5
A7: BK1061 | B7: 45910 | C7: 218 | D7: King | E7: Booking.com | F7: Australia | G7: 2 | H7: 139.08 | I7: 8.5 | J7: Completed | K7: Paid | L7: 4 | M7: 45882 | N7: 45914 | O7: 4 | P7: 564.82 | R7: Paid
A8: BK1016 | B8: 45728 | C8: 111 | D8: King | E8: Walk-in | F8: United States | G8: 3 | H8: 136.43 | I8: 8.5 | J8: Completed | K8: Paid | L8: 4 | M8: 45692 | N8: 45732 | O8: 4 | P8: 554.22
A9: BK1024 | B9: 46001 | C9: 113 | D9: King | E9: Expedia | F9: United Kingdom | G9: 3 | H9: 135.75 | I9: 8.5 | J9: Completed | K9: Paid | L9: 3 | M9: 45991 | N9: 46005 | O9: 4 | P9: 551.5
A10: BK1052 | B10: 45938 | C10: 219 | D10: Deluxe | E10: Walk-in | F10: United States | G10: 2 | H10: 108.08 | I10: 8.5 | J10: Completed | K10: Paid | M10: 45886 | N10: 45943 | O10: 5 | P10: 548.9
A11: BK1093 | B11: 45810 | C11: 105 | D11: Double | E11: Booking.com | F11: Germany | G11: 2 | H11: 104.17 | I11: 8.5 | J11: Completed | K11: Paid | L11: 4 | M11: 45799 | N11: 45815 | O11: 5 | P11: 529.35
A12: BK1111 | B12: 45987 | C12: 201 | D12: Double | E12: Booking.com | F12: Canada | G12: 4 | H12: 103.16 | I12: 8.5 | J12: Completed | K12: Paid | L12: 5 | M12: 45951 | N12: 45992 | O12: 5 | P12: 524.3
A13: BK1068 | B13: 45690 | C13: 109 | D13: Unknown | E13: Direct | F13: Australia | G13: 1 | H13: 102.22 | I13: 8.5 | J13: Completed | K13: Paid | L13: 4 | M13: 45671 | N13: 45695 | O13: 5 | P13: 519.6
A14: BK1083 | B14: 45812 | C14: 118 | D14: Double | E14: Walk-in | F14: Canada | G14: 2 | H14: 98.7 | I14: 8.5 | J14: Completed | K14: Paid | L14: 5 | M14: 45766 | N14: 45817 | O14: 5 | P14: 502
A15: BK1119 | B15: 45953 | C15: 104 | D15: Deluxe | E15: Expedia | F15: Australia | G15: 3 | H15: 96.49 | I15: 8.5 | J15: Completed | K15: Paid | L15: 4 | M15: 45947 | N15: 45958 | O15: 5 | P15: 490.95
A16: BK1025 | B16: 45962 | C16: 214 | D16: Deluxe | E16: Direct | F16: Germany | G16: 1 | H16: 120.54 | I16: 8.5 | J16: Completed | K16: Paid | L16: 4 | M16: 45929 | N16: 45966 | O16: 4 | P16: 490.66
A17: BK1112 | B17: 45996 | C17: 114 | D17: Double | E17: Walk-in | F17: United States | G17: 2 | H17: 95.17 | I17: 8.5 | J17: Completed | K17: Paid | L17: 3 | M17: 45949 | N17: 46001 | O17: 5 | P17: 484.35
A18: BK1089 | B18: 46008 | C18: 201 | D18: Double | E18: Direct | F18: Germany | G18: 1 | H18: 92.04 | I18: 8.5 | J18: Completed | K18: Paid | L18: 4 | M18: 45983 | N18: 46013 | O18: 5 | P18: 468.7
A19: BK1031 | B19: 45798 | C19: 117 | D19: Standard | E19: Direct | F19: France | G19: 2 | H19: 90.73 | I19: 8.5 | J19: Completed | K19: Paid | L19: 4 | M19: 45766 | N19: 45803 | O19: 5 | P19: 462.15
A20: BK1060 | B20: 45717 | C20: 210 | D20: Deluxe | E20: Walk-in | F20: United States | G20: 4 | H20: 110.65 | I20: 8.5 | J20: Completed | K20: Paid | L20: 5 | M20: 45693 | N20: 45721 | O20: 4 | P20: 451.1
A21: BK1063 | B21: 45806 | C21: 118 | D21: Standard | E21: Expedia | F21: United Kingdom | G21: 2 | H21: 88 | I21: 8.5 | J21: Completed | K21: Paid | L21: 5 | M21: 45761 | N21: 45811 | O21: 5 | P21: 448.5
A22: BK1080 | B22: 45663 | C22: 207 | D22: Standard | E22: Expedia | F22: Germany | G22: 2 | H22: 85.57 | I22: 8.5 | J22: Completed | K22: Paid | L22: 3 | M22: 45633 | N22: 45668 | O22: 5 | P22: 436.35
... A38: BK1037 | B38: 45842 | C38: 115 | D38: Deluxe | E38: Direct | F38: France | G38: 2 | H38: 106.95 | I38: 8.5 | J38: Completed | K38: Paid | L38: 4 | M38: 45789 | N38: 45845 | O38: 3 | P38: 329.35
A39: BK1094 | B39: 45764 | C39: 211 | D39: Standard | E39: Expedia | F39: Canada | G39: 3 | H39: 78.97 | I39: 8.5 | J39: Completed | K39: Paid | M39: 45709 | N39: 45768 | O39: 4 | P39: 324.38
A40: BK1104 | B40: 45890 | C40: 204 | D40: Standard | E40: Booking.com | F40: Germany | G40: 4 | H40: 78.97 | I40: 8.5 | J40: Completed | K40: Paid | L40: 3 | M40: 45874 | N40: 45894 | O40: 4 | P40: 324.38
A41: BK1075 | B41: 45954 | C41: 108 | D41: Double | E41: Booking.com | F41: France | G41: 2 | H41: 103.81 | I41: 8.5 | J41: Completed | K41: Paid | L41: 3 | M41: 45925 | N41: 45957 | O41: 3 | P41: 319.93
A42: BK1097 | B42: 45959 | C42: 109 | D42: Standard | E42: Booking.com | F42: India | G42: 4 | H42: 103.81 | I42: 8.5 | J42: Completed | K42: Paid | L42: 4 | M42: 45912 | N42: 45962 | O42: 3 | P42: 319.93
A43: BK1079 | B43: 45873 | C43: 206 | D43: Standard | E43: Walk-in | F43: United Kingdom | G43: 2 | H43: 76.31 | I43: 8.5 | J43: Completed | K43: Paid | L43: 5 | M43: 45854 | N43: 45877 | O43: 4 | P43: 313.74
A44: BK1029 | B44: 45788 | C44: 111 | D44: Unknown | E44: Booking.com | F44: Germany | G44: 4 | H44: 100.87 | I44: 8.5 | J44: Completed | K44: Paid | L44: 5 | M44: 45769 | N44: 45791 | O44: 3 | P44: 311.11
A45: BK1082 | B45: 45744 | C45: 101 | D45: Double | E45: Unknown | F45: United States | G45: 1 | H45: 98.84 | I45: 8.5 | J45: Completed | K45: Paid | L45: 4 | M45: 45708 | N45: 45747 | O45: 3 | P45: 305.02
A46: BK1027 | B46: 45767 | C46: 117 | D46: Double | E46: Expedia | F46: France | G46: 4 | H46: 94 | I46: 8.5 | J46: Completed | K46: Paid | L46: 3 | M46: 45751 | N46: 45770 | O46: 3 | P46: 290.5
A47: BK1070 | B47: 45951 | C47: 116 | D47: Standard | E47: Walk-in | F47: Germany | G47: 3 | H47: 89.77 | I47: 8.5 | J47: Completed | K47: Paid | L47: 4 | M47: 45945 | N47: 45954 | O47: 3 | P47: 277.81
A48: BK1003 | B48: 45877 | C48: 218 | D48: King | E48: Direct | F48: Australia | G48: 2 | H48: 134.43 | I48: 8.5 | J48: Completed | K48: Paid | L48: 4 | M48: 45848 | N48: 45879 | O48: 2 | P48: 277.36
A49: BK1017 | B49: 46006 | C49: 214 | D49: Deluxe | E49: Direct | F49: United States | G49: 2 | H49: 86.92 | I49: 8.5 | J49: Completed | K49: Paid | L49: 5 | M49: 45977 | N49: 46009 | O49: 3 | P49: 269.26
A50: BK1087 | B50: 46002 | C50: 103 | D50: Deluxe | E50: Booking.com | F50: Australia | G50: 1 | H50: 121.23 | I50: 8.5 | J50: Completed | K50: Paid | L50: 4 | M50: 45970 | N50: 46004 | O50: 2 | P50: 250.96
A51: BK1042 | B51: 45857 | C51: 217 | D51: King | E51: Walk-in | F51: Germany | G51: 1 | H51: 120.64 | I51: 8.5 | J51: Completed | K51: Paid | L51: 5 | M51: 45817 | N51: 45859 | O51: 2 | P51: 249.78
... A99: BK1040 | B99: 45793 | C99: 208 | D99: Standard | E99: Expedia | F99: India | G99: 2 | H99: 71.75 | I99: 8.5 | J99: Completed | K99: Paid | L99: 4 | M99: 45747 | N99: 45794 | O99: 1 | P99: 80.25
A100: BK1007 | B100: 45994 | C100: 111 | D100: Deluxe | E100: Expedia | F100: Canada | G100: 2 | H100: 103.1 | I100: 8.5 | J100: Cancelled | K100: Refunded | M100: 45955 | N100: 45995 | O100: 1 | P100: 0
A101: BK1014 | B101: 45939 | C101: 101 | D101: King | E101: Walk-in | F101: United Kingdom | G101: 1 | H101: 142.52 | I101: 8.5 | J101: Cancelled | K101: Pending | M101: 45880 | N101: 45944 | O101: 5 | P101: 0
A102: BK1015 | B102: 45785 | C102: 217 | D102: Standard | E102: Direct | F102: France | G102: 2 | H102: 90.4 | I102: 8.5 | J102: No-Show | K102: Pending | M102: 45769 | N102: 45786 | O102: 1 | P102: 0
A103: BK1020 | B103: 45844 | C103: 210 | D103: Standard | E103: Direct | F103: United Kingdom | G103: 2 | H103: 88.21 | I103: 8.5 | J103: Cancelled | K103: Refunded | M103: 45817 | N103: 45848 | O103: 4 | P103: 0
A104: BK1033 | B104: 45852 | C104: 110 | D104: Double | E104: Expedia | F104: United Kingdom | G104: 2 | H104: 95.94 | I104: 8.5 | J104: Cancelled | K104: Refunded | M104: 45816 | N104: 45857 | O104: 5 | P104: 0
A105: BK1035 | B105: 45784 | C105: 112 | D105: Double | E105: Direct | F105: United States | G105: 4 | H105: 112.73 | I105: 8.5 | J105: Cancelled | K105: Pending | M105: 45732 | N105: 45786 | O105: 2 | P105: 0
A106: BK1038 | B106: 45842 | C106: 215 | D106: King | E106: Direct | F106: United Kingdom | G106: 2 | H106: 116.25 | I106: 8.5 | J106: No-Show | K106: Paid | M106: 45816 | N106: 45847 | O106: 5 | P106: 0
A107: BK1043 | B107: 45998 | C107: 209 | D107: Double | E107: Expedia | F107: Germany | G107: 2 | H107: 108.81 | I107: 8.5 | J107: No-Show | K107: Pending | M107: 45968 | N107: 46001 | O107: 3 | P107: 0
A108: BK1044 | B108: 46000 | C108: 213 | D108: King | E108: Direct | F108: Australia | G108: 2 | H108: 133.55 | I108: 8.5 | J108: Cancelled | K108: Paid | L108: 3 | M108: 45981 | N108: 46001 | O108: 1 | P108: 0
A109: BK1049 | B109: 45983 | C109: 209 | D109: Standard | E109: Booking.com | F109: United States | G109: 2 | H109: 78.4 | I109: 8.5 | J109: Cancelled | K109: Refunded | M109: 45965 | N109: 45985 | O109: 2 | P109: 0
A110: BK1055 | B110: 45792 | C110: 102 | D110: Standard | E110: Booking.com | F110: United States | G110: 4 | H110: 71.72 | I110: 8.5 | J110: No-Show | K110: Pending | M110: 45761 | N110: 45793 | O110: 1 | P110: 0
A111: BK1057 | B111: 45794 | C111: 219 | D111: Standard | E111: Expedia | F111: Unknown | G111: 1 | H111: 84.47 | I111: 8.5 | J111: Cancelled | K111: Pending | M111: 45783 | N111: 45797 | O111: 3 | P111: 0
A112: BK1059 | B112: 45684 | C112: 208 | D112: King | E112: Direct | F112: Germany | G112: 4 | H112: 103.81 | I112: 8.5 | J112: Cancelled | K112: Pending | M112: 45649 | N112: 45687 | O112: 3 | P112: 0
A113: BK1071 | B113: 45889 | C113: 218 | D113: Double | E113: Booking.com | F113: Germany | G113: 3 | H113: 86.81 | I113: 8.5 | J113: No-Show | K113: Pending | M113: 45833 | N113: 45892 | O113: 3 | P113: 0
A114: BK1078 | B114: 45988 | C114: 211 | D114: King | E114: Walk-in | F114: India | G114: 2 | H114: 133.45 | I114: 8.5 | J114: Cancelled | K114: Pending | M114: 45982 | N114: 45992 | O114: 4 | P114: 0
A115: BK1081 | B115: 45767 | C115: 109 | D115: King | E115: Walk-in | F115: France | G115: 2 | H115: 114.25 | I115: 8.5 | J115: No-Show | K115: Pending | M115: 45731 | N115: 45770 | O115: 3 | P115: 0
A116: BK1090 | B116: 45709 | C116: 107 | D116: Double | E116: Expedia | F116: France | G116: 2 | H116: 112.1 | I116: 8.5 | J116: No-Show | K116: Paid | L116: 4 | M116: 45702 | N116: 45713 | O116: 4 | P116: 0
A117: BK1096 | B117: 45988 | C117: 117 | D117: Deluxe | E117: Direct | F117: France | G117: 4 | H117: 96.18 | I117: 8.5 | J117: Cancelled | K117: Refunded | M117: 45948 | N117: 45990 | O117: 2 | P117: 0
A118: BK1107 | B118: 45729 | C118: 112 | D118: Standard | E118: Direct | F118: United States | G118: 1 | H118: 78.96 | I118: 8.5 | J118: Cancelled | K118: Pending | M118: 45712 | N118: 45734 | O118: 5 | P118: 0
A119: BK1113 | B119: 45823 | C119: 117 | D119: King | E119: Expedia | F119: France | G119: 2 | H119: 112.35 | I119: 8.5 | J119: Cancelled | K119: Refunded | M119: 45802 | N119: 45827 | O119: 4 | P119: 0
A120: BK1116 | B120: 45842 | C120: 108 | D120: King | E120: Expedia | F120: Australia | G120: 2 | H120: 139.58 | I120: 8.5 | J120: No-Show | K120: Pending | M120: 45818 | N120: 45847 | O120: 5 | P120: 0
A121: BK1117 | B121: 45974 | C121: 112 | D121: King | E121: Booking.com | F121: India | G121: 2 | H121: 110.21 | I121: 8.5 | J121: Cancelled | K121: Pending | M121: 45972 | N121: 45977 | O121: 3 | P121: 0

Sheet Excel_Analysis
A1: Motel KPI Summary
A3: Total Revenue | B3: =SUM(Cleaned_Motel_Data[Estimated_Revenue_GBP]) -> 28774.55
A4: Total Bookings | B4: =COUNTA(Cleaned_Motel_Data[Booking_ID]) -> 120
A5: Completed Bookings | B5: =COUNTIF(Cleaned_Motel_Data[Booking_Status],"Completed") -> 98
A6: Cancelled Bookings | B6: =COUNTIF(Cleaned_Motel_Data[Booking_Status],"Cancelled") -> 14
A7: No-Show Bookings | B7: =COUNTIF(Cleaned_Motel_Data[Booking_Status],"No-Show") -> 8
A8: Average Nightly Rate | B8: =ROUND(AVERAGE(Cleaned_Motel_Data[Nightly_Rate_GBP]),2) -> 103.81
A9: Average Guest Rating | B9: =ROUND(AVERAGE(Cleaned_Motel_Data[Guest_Rating]),2) -> 4.15
A10: Cancellation Rate | B10: =B6/B4 -> 0.11666667

Sheet Excel_Dashboard
A1: Motel Booking Analytics Dashboard
A4: Total Revenue | D4: Total Bookings | G4: Completed Bookings | J4: Cancellation Rate | M4: Average Guest Rating
A5: =Pivot_KPI!A2 -> 28774.55 | D5: =Pivot_KPI!D2 -> 120 | G5: =Pivot_KPI!G4 -> 98 | J5: =IFERROR(Pivot_KPI!J4/Pivot_KPI!D2,0) -> 0.11666667 | M5: =Pivot_KPI!M2 -> 4.1530612

Sheet Business_Insights
A1: Motel Booking Analytics – Business Insights
A3: Key Findings
A4: Total revenue was £28,774.55 from 120 bookings.
A5: 98 bookings were completed, while 14 were cancelled and 8 were no-shows.
A6: The cancellation rate was 11.67%.
A7: October generated the highest monthly revenue.
A8: April generated the lowest monthly revenue.
A9: Walk-in bookings generated the highest revenue.
A10: Booking.com and Expedia received the highest number of bookings.
A11: Deluxe rooms generated the highest revenue among known room types.
A12: Deluxe rooms also had the highest average rating among known room types.
A13: Overall average guest rating was 4.15.
... A23: Source: Motel Booking Analytics Excel Dashboard

Sheet Excel_Formula_Practice
A1: Formula | B1: Bussiness Question | C1: Result | D1: Meaning | E1: Revenue Target | H1: Messy Text
A2: SUMIF | B2: What is the total revenue from Deluxe rooms? | C2: =SUMIF(Cleaned_Motel_Data[Room_Type],"Deluxe",Cleaned_Motel_Data[Estimated_Revenue_GBP]) -> 7366.9 | D2: adds numbers only when one condition is satisfied | E2: 7000 | F2: BK1026 | H2: deluxe | J2: No-Show
A3: SUMIFS | B3: What is the total revenue from completed Booking.com reservations? | C3: =SUMIFS(Cleaned_Motel_Data[Estimated_Revenue_GBP],Cleaned_Motel_Data[Booking_Status],"Completed",Cleaned_Motel_Data[Booking_Source],"Booking.com") -> 7358.8 | D3: adds numbers using more than one condition | H3: deluxe room
A4: COUNTIFS | B4: How many completed Deluxe room bookings are there? | C4: =COUNTIFS(Cleaned_Motel_Data[Booking_Status],"Completed",Cleaned_Motel_Data[Room_Type],"Deluxe") -> 28 | D4: counts rows using more than one condition | H4: booking.com | J4: Nightly Rate | K4: 100
A5: AVERAGEIF | B5: What is the average guest rating for Deluxe rooms? | C5: =AVERAGEIF(Cleaned_Motel_Data[Room_Type],"Deluxe",Cleaned_Motel_Data[Guest_Rating]) -> 4.3333333 | D5: calculates an average using one condition | H5: BOOKING.COM | J5: Nights | K5: 5
A6: AVERAGEIFS | B6: What is the average nightly rate for completed Deluxe bookings? | C6: =AVERAGEIFS(Cleaned_Motel_Data[Nightly_Rate_GBP],Cleaned_Motel_Data[Booking_Status],"Completed",Cleaned_Motel_Data[Room_Type],"Deluxe") -> 109.0275 | D6: calculates an average using more than one condition | H6: BK1015 | J6: Revenue | K6: =K4*K5 -> 500
A7: MIN | B7: What is the lowest nightly room rate? | C7: =MIN(Cleaned_Motel_Data[Nightly_Rate_GBP]) -> 71.72 | D7: finds the smallest number | H7: =DATE(2025,8,5) -> 45874
A8: MAX | B8: What is the highest nightly room rate? | C8: =MAX(Cleaned_Motel_Data[Nightly_Rate_GBP]) -> 144.45 | D8: finds the largest number | H8: =DATE(2025,8,10) -> 45879
A9: ROUND | B9: What is the average nightly rate rounded to 2 decimal places? | C9: =ROUND(AVERAGE(Cleaned_Motel_Data[Nightly_Rate_GBP]),2) -> 103.81 | D9: calculates the average nightly rate and keeps only 2 decimal places
A10: IF | B10: Are cancellations high or low? | C10: =IF(COUNTIF(Cleaned_Motel_Data[Booking_Status],"Cancelled")>10,"High Cancellations","Low Cancellations") -> High Cancellations | D10: gives one result when a condition is true and another when it is false
A11: IFS | B11: How is Deluxe room revenue performing? | C11: {=_xlfn.IFS(C2>=7500,"Excellent",C2>=6500,"Good",TRUE,"Needs Attention")} -> Good | D11: checks multiple conditions
A12: Absolute Reference | B12: Did Deluxe room revenue meet the £7,000 target? | C12: =IF(C2>=$E$2,"Target Met","Below Target") -> Target Met | D12: keeps the target cell fixed when the formula is copied
A13: XLOOKUP | B13: What is the room type for the Booking ID entered in F2? | C13: =_xlfn.XLOOKUP(F2,Cleaned_Motel_Data[Booking_ID],Cleaned_Motel_Data[Room_Type]) -> Deluxe | D13: searches for a value and returns matching information
A14: IFERROR | B14: What should Excel show when a Booking ID is not found? | C14: =IFERROR(_xlfn.XLOOKUP(F2,Cleaned_Motel_Data[Booking_ID],Cleaned_Motel_Data[Room_Type]),"Booking ID Not Found") -> Deluxe | D14: replaces an Excel error with a clear message
A15: TRIM | B15: How can we remove extra spaces from text? | C15: =TRIM(H2) -> deluxe | D15: removes unnecessary spaces from text
A16: PROPER | B16: How can we capitalize the first letter of each word? | C16: =PROPER(H3) -> Deluxe Room | D16: capitalizes the first letter of every word
A17: UPPER | B17: How can we convert text into capital letters? | C17: =UPPER(H4) -> BOOKING.COM | D17: converts all letters into uppercase
A18: LOWER | B18: How can we convert text into small letters? | C18: =LOWER(H5) -> booking.com | D18: converts all letters into lowercase
A19: LEFT | B19: How can we extract the first two characters from a Booking ID? | C19: =LEFT(F2,2) -> BK | D19: extracts characters from the beginning of text
A20: RIGHT | B20: How can we extract the last four characters from a Booking ID? | C20: =RIGHT(F2,4) -> 1026 | D20: extracts characters from the end of text
A21: MID | B21: How can we extract characters from the middle of a Booking ID? | C21: =MID(F2,3,4) -> 1026 | D21: extracts characters from the middle of text
A22: LEN | B22: How many characters are in the Booking ID? | C22: =LEN(F2) -> 6 | D22: counts the number of characters in text
A23: CONCAT or TEXTJOIN | B23: How can we combine the Booking ID and Room Type? | C23: =_xlfn.CONCAT(F2," - ",C13) -> BK1026 - Deluxe | D23: joins text from different cells together
A24: YEAR | B24: What year is the check-in date? | C24: =YEAR(H7) -> 2025 | D24: extracts the year from a date
A25: MONTH | B25: What month is the check-in date? | C25: =MONTH(H7) -> 8 | D25: extracts the month number from a date
A26: DAY | B26: What day is the check-in date? | C26: =DAY(H7) -> 5 | D26: extracts the day number from a date
A27: TODAY | B27: What is today’s date? | C27: =TODAY() -> 46248 | D27: returns the current date automatically
A28: DATEDIF | B28: How many days are between the two dates? | C28: =DATEDIF(H7,H8,"d") -> 5 | D28: calculates the number of days between two dates
A29: EOMONTH | B29: What is the last day of the check-in month? | C29: =EOMONTH(H7,0) -> 45900 | D29: returns the last date of a month

Sheet Pivot_KPI
A1: Sum of Estimated_Revenue_GBP | D1: Count of Booking_ID | G1: Booking_Status | H1: Completed | J1: Booking_Status | K1: Cancelled | M1: Average of Guest_Rating
A2: 28774.55 | D2: 120 | M2: 4.1530612
G3: Count of Booking_ID | J3: Count of Booking_ID
G4: 98 | J4: 14

Sheet Pivot_Room_Type
A3: Row Labels | B3: Sum of Estimated_Revenue_GBP
A4: Deluxe | B4: 7366.9
A5: Double | B5: 6627.72
A6: King | B6: 6609.93
A7: Standard | B7: 7009.7
A8: Unknown | B8: 1160.3
A9: Grand Total | B9: 28774.55

Sheet Pivot_Booking_Source
A3: Row Labels | B3: Count of Booking_ID
A4: Booking.com | B4: 30
A5: Direct | B5: 28
A6: Expedia | B6: 30
A7: Unknown | B7: 3
A8: Walk-in | B8: 29
A9: Grand Total | B9: 120

Sheet Pivot_Booking_Status
A3: Row Labels | B3: Count of Booking_ID
A4: Cancelled | B4: 14
A5: Completed | B5: 98
A6: No-Show | B6: 8
A7: Grand Total | B7: 120

Sheet Pivot_Monthly_Revenue
A3: Row Labels | B3: Sum of Estimated_Revenue_GBP
A4: Jan | B4: 2086.31
A5: Feb | B5: 2022.94
A6: Mar | B6: 1855.21
A7: Apr | B7: 1166.69
A8: May | B8: 2323.92
A9: Jun | B9: 1336.26
A10: Jul | B10: 1502.27
A11: Aug | B11: 2993.44
A12: Sep | B12: 2455.76
A13: Oct | B13: 4162.18
A14: Nov | B14: 3293.11
A15: Dec | B15: 3576.46
A16: Grand Total | B16: 28774.55

Sheet Pivot_Room_Rating
A3: Row Labels | B3: Average of Guest_Rating
A4: Deluxe | B4: 4.3333333
A5: Double | B5: 4.0909091
A6: King | B6: 4.1
A7: Standard | B7: 4
A8: Unknown | B8: 4.6666667
A9: Grand Total | B9: 4.1530612

Sheet Detail1
A1: Details for Sum of Estimated_Revenue_GBP
A3: Booking_ID | B3: Check_In_Date | C3: Room_Number | D3: Room_Type | E3: Booking_Source | F3: Guest_Country | G3: Adults | H3: Nightly_Rate_GBP | I3: Resort_Fee_GBP | J3: Booking_Status | K3: Payment_Status | L3: Guest_Rating | M3: Booking_Date | N3: Check_Out_Date | O3: Nights | P3: Estimated_Revenue_GBP
A4: BK1002 | B4: 45879 | C4: 106 | D4: Deluxe | E4: Expedia | F4: Germany | G4: 3 | H4: 95.8 | I4: 8.5 | J4: Completed | K4: Paid | L4: 5 | M4: 45877 | N4: 45880 | O4: 1 | P4: 104.3
A5: BK1114 | B5: 45884 | C5: 204 | D5: Deluxe | E5: Direct | F5: Germany | G5: 3 | H5: 111.85 | I5: 8.5 | J5: Completed | K5: Paid | L5: 5 | M5: 45836 | N5: 45885 | O5: 1 | P5: 120.35
A6: BK1091 | B6: 45846 | C6: 110 | D6: Deluxe | E6: Walk-in | F6: Germany | G6: 4 | H6: 118.78 | I6: 8.5 | J6: Completed | K6: Paid | L6: 4 | M6: 45818 | N6: 45849 | O6: 3 | P6: 364.84
A7: BK1066 | B7: 45824 | C7: 215 | D7: Deluxe | E7: Expedia | F7: United States | G7: 4 | H7: 109.53 | I7: 8.5 | J7: Completed | K7: Pending | L7: 5 | M7: 45776 | N7: 45825 | O7: 1 | P7: 118.03
A8: BK1058 | B8: 45866 | C8: 218 | D8: Deluxe | E8: Direct | F8: France | G8: 2 | H8: 120.51 | I8: 8.5 | J8: Completed | K8: Paid | L8: 5 | M8: 45861 | N8: 45868 | O8: 2 | P8: 249.52
A9: BK1053 | B9: 45870 | C9: 210 | D9: Deluxe | E9: Walk-in | F9: Canada | G9: 3 | H9: 111.93 | I9: 8.5 | J9: Completed | K9: Paid | L9: 4 | M9: 45816 | N9: 45872 | O9: 2 | P9: 232.36
A10: BK1037 | B10: 45842 | C10: 115 | D10: Deluxe | E10: Direct | F10: France | G10: 2 | H10: 106.95 | I10: 8.5 | J10: Completed | K10: Paid | L10: 4 | M10: 45789 | N10: 45845 | O10: 3 | P10: 329.35
A11: BK1026 | B11: 45869 | C11: 217 | D11: Deluxe | E11: Direct | F11: Germany | G11: 1 | H11: 107.58 | I11: 8.5 | J11: Completed | K11: Paid | L11: 4 | M11: 45753 | N11: 45870 | O11: 1 | P11: 116.08
A12: BK1009 | B12: 45824 | C12: 212 | D12: Double | E12: Walk-in | F12: United States | G12: 2 | H12: 89.19 | I12: 8.5 | J12: Completed | K12: Paid | L12: 5 | M12: 45782 | N12: 45826 | O12: 2 | P12: 186.88
A13: BK1093 | B13: 45810 | C13: 105 | D13: Double | E13: Booking.com | F13: Germany | G13: 2 | H13: 104.17 | I13: 8.5 | J13: Completed | K13: Paid | L13: 4 | M13: 45799 | N13: 45815 | O13: 5 | P13: 529.35
A14: BK1083 | B14: 45812 | C14: 118 | D14: Double | E14: Walk-in | F14: Canada | G14: 2 | H14: 98.7 | I14: 8.5 | J14: Completed | K14: Paid | L14: 5 | M14: 45766 | N14: 45817 | O14: 5 | P14: 502
A15: BK1071 | B15: 45889 | C15: 218 | D15: Double | E15: Booking.com | F15: Germany | G15: 3 | H15: 86.81 | I15: 8.5 | J15: No-Show | K15: Pending | M15: 45833 | N15: 45892 | O15: 3 | P15: 0
A16: BK1054 | B16: 45899 | C16: 117 | D16: Double | E16: Booking.com | F16: United States | G16: 2 | H16: 94.81 | I16: 8.5 | J16: Completed | K16: Paid | L16: 4 | M16: 45895 | N16: 45901 | O16: 2 | P16: 198.12
A17: BK1048 | B17: 45891 | C17: 211 | D17: Double | E17: Booking.com | F17: Australia | G17: 2 | H17: 110.2 | I17: 8.5 | J17: Completed | K17: Paid | L17: 4 | M17: 45843 | N17: 45893 | O17: 2 | P17: 228.9
A18: BK1033 | B18: 45852 | C18: 110 | D18: Double | E18: Expedia | F18: United Kingdom | G18: 2 | H18: 95.94 | I18: 8.5 | J18: Cancelled | K18: Refunded | M18: 45816 | N18: 45857 | O18: 5 | P18: 0
A19: BK1116 | B19: 45842 | C19: 108 | D19: King | E19: Expedia | F19: Australia | G19: 2 | H19: 139.58 | I19: 8.5 | J19: No-Show | K19: Pending | M19: 45818 | N19: 45847 | O19: 5 | P19: 0
A20: BK1003 | B20: 45877 | C20: 218 | D20: King | E20: Direct | F20: Australia | G20: 2 | H20: 134.43 | I20: 8.5 | J20: Completed | K20: Paid | L20: 4 | M20: 45848 | N20: 45879 | O20: 2 | P20: 277.36
A21: BK1115 | B21: 45879 | C21: 219 | D21: King | E21: Booking.com | F21: United Kingdom | G21: 3 | H21: 127.76 | I21: 8.5 | J21: Completed | K21: Paid | L21: 3 | M21: 45860 | N21: 45880 | O21: 1 | P21: 136.26
A22: BK1113 | B22: 45823 | C22: 117 | D22: King | E22: Expedia | F22: France | G22: 2 | H22: 112.35 | I22: 8.5 | J22: Cancelled | K22: Refunded | M22: 45802 | N22: 45827 | O22: 4 | P22: 0
A23: BK1062 | B23: 45900 | C23: 205 | D23: King | E23: Direct | F23: Canada | G23: 2 | H23: 116.36 | I23: 8.5 | J23: Completed | K23: Pending | L23: 4 | M23: 45860 | N23: 45905 | O23: 5 | P23: 590.3
A24: BK1042 | B24: 45857 | C24: 217 | D24: King | E24: Walk-in | F24: Germany | G24: 1 | H24: 120.64 | I24: 8.5 | J24: Completed | K24: Paid | L24: 5 | M24: 45817 | N24: 45859 | O24: 2 | P24: 249.78
A25: BK1038 | B25: 45842 | C25: 215 | D25: King | E25: Direct | F25: United Kingdom | G25: 2 | H25: 116.25 | I25: 8.5 | J25: No-Show | K25: Paid | M25: 45816 | N25: 45847 | O25: 5 | P25: 0
A26: BK1105 | B26: 45895 | C26: 114 | D26: Standard | E26: Direct | F26: Australia | G26: 2 | H26: 76.09 | I26: 8.5 | J26: Completed | K26: Paid | L26: 3 | M26: 45895 | N26: 45896 | O26: 1 | P26: 84.59
A27: BK1104 | B27: 45890 | C27: 204 | D27: Standard | E27: Booking.com | F27: Germany | G27: 4 | H27: 78.97 | I27: 8.5 | J27: Completed | K27: Paid | L27: 3 | M27: 45874 | N27: 45894 | O27: 4 | P27: 324.38
A28: BK1079 | B28: 45873 | C28: 206 | D28: Standard | E28: Walk-in | F28: United Kingdom | G28: 2 | H28: 76.31 | I28: 8.5 | J28: Completed | K28: Paid | L28: 5 | M28: 45854 | N28: 45877 | O28: 4 | P28: 313.74
A29: BK1020 | B29: 45844 | C29: 210 | D29: Standard | E29: Direct | F29: United Kingdom | G29: 2 | H29: 88.21 | I29: 8.5 | J29: Cancelled | K29: Refunded | M29: 45817 | N29: 45848 | O29: 4 | P29: 0
A30: BK1051 | B30: 45878 | C30: 218 | D30: Standard | E30: Walk-in | F30: Canada | G30: 1 | H30: 93.57 | I30: 8.5 | J30: Completed | K30: Paid | L30: 4 | M30: 45820 | N30: 45882 | O30: 4 | P30: 382.78
A31: BK1034 | B31: 45846 | C31: 116 | D31: Standard | E31: Booking.com | F31: Australia | G31: 3 | H31: 92.1 | I31: 8.5 | J31: Completed | K31: Paid | L31: 4 | M31: 45802 | N31: 45848 | O31: 2 | P31: 192.7

Sheet Excel_Charts
